galois/__init__.py
galois/_helper.py
galois/_lfsr.py
galois/_math.py
galois/_modular.py
galois/_ntt.py
galois/_options.py
galois/_polymorphic.py
galois/_prime.py
galois/_primitive_root.py
galois/_version.py
galois/py.typed
galois/typing.py
galois/_codes/__init__.py
galois/_codes/_bch.py
galois/_codes/_cyclic.py
galois/_codes/_linear.py
galois/_codes/_reed_solomon.py
galois/_databases/__init__.py
galois/_databases/_interface.py
galois/_databases/conway_polys.db
galois/_databases/irreducible_polys.db
galois/_databases/prime_factors.db
galois/_domains/__init__.py
galois/_domains/_array.py
galois/_domains/_calculate.py
galois/_domains/_factory.py
galois/_domains/_function.py
galois/_domains/_linalg.py
galois/_domains/_lookup.py
galois/_domains/_meta.py
galois/_domains/_ufunc.py
galois/_fields/__init__.py
galois/_fields/_array.py
galois/_fields/_factory.py
galois/_fields/_gf2.py
galois/_fields/_meta.py
galois/_fields/_normal_element.py
galois/_fields/_primitive_element.py
galois/_fields/_ufunc.py
galois/_polys/__init__.py
galois/_polys/_binary.py
galois/_polys/_conversions.py
galois/_polys/_conway.py
galois/_polys/_dense.py
galois/_polys/_factor.py
galois/_polys/_functions.py
galois/_polys/_irreducible.py
galois/_polys/_lagrange.py
galois/_polys/_poly.py
galois/_polys/_primitive.py
galois/_polys/_search.py
galois/_polys/_sparse.py
galois-0.4.9.dist-info/licenses/LICENSE
galois-0.4.9.dist-info/METADATA
galois-0.4.9.dist-info/WHEEL
galois-0.4.9.dist-info/top_level.txt
galois-0.4.9.dist-info/RECORD
