Metadata-Version: 2.4
Name: galois
Version: 0.4.9
Summary: A performant NumPy extension for Galois fields and their applications
Author-email: Matt Hostetter <matthostetter@gmail.com>
License: MIT
Project-URL: Homepage, https://github.com/mhostetter/galois
Project-URL: Source, https://github.com/mhostetter/galois
Project-URL: Issues, https://github.com/mhostetter/galois/issues
Project-URL: Documentation, https://mhostetter.github.io/galois/latest/
Project-URL: Discuss, https://github.com/mhostetter/galois/discussions
Project-URL: Changelog, https://mhostetter.github.io/galois/latest/release-notes/versioning/
Project-URL: Twitter, https://twitter.com/galois_py
Keywords: aes,bch,cryptography,ecc,elliptic curve cryptography,elliptic curves,encryption,error correction,fec,finite field,galois field,golay,hamming,numpy,reed solomon,rsa
Classifier: Development Status :: 4 - Beta
Classifier: Intended Audience :: Developers
Classifier: Intended Audience :: Education
Classifier: Intended Audience :: Science/Research
Classifier: Intended Audience :: Telecommunications Industry
Classifier: License :: OSI Approved :: MIT License
Classifier: Operating System :: MacOS :: MacOS X
Classifier: Operating System :: Microsoft :: Windows
Classifier: Operating System :: POSIX :: Linux
Classifier: Programming Language :: Python :: 3
Classifier: Programming Language :: Python :: 3 :: Only
Classifier: Programming Language :: Python :: 3.7
Classifier: Programming Language :: Python :: 3.8
Classifier: Programming Language :: Python :: 3.9
Classifier: Programming Language :: Python :: 3.10
Classifier: Programming Language :: Python :: 3.11
Classifier: Programming Language :: Python :: 3.12
Classifier: Programming Language :: Python :: 3.13
Classifier: Programming Language :: Python :: 3.14
Classifier: Topic :: Scientific/Engineering :: Mathematics
Classifier: Topic :: Security :: Cryptography
Classifier: Topic :: Software Development :: Libraries :: Python Modules
Classifier: Typing :: Typed
Requires-Python: >=3.7
License-File: LICENSE
Requires-Dist: numpy>=1.21.0
Requires-Dist: numba>=0.55
Requires-Dist: typing_extensions>=4.0.0
Dynamic: license-file
